<p:animRot by="120000"><p:cBhvr><p:cTn id="{ID0}" dur="100" fill="hold"><p:stCondLst><p:cond delay="0" /></p:stCondLst></p:cTn><p:tgtEl><p:spTgt spid="{SPID}" /></p:tgtEl><p:attrNameLst><p:attrName>r</p:attrName></p:attrNameLst></p:cBhvr></p:animRot><p:animRot by="-240000"><p:cBhvr><p:cTn id="{ID1}" dur="200" fill="hold"><p:stCondLst><p:cond delay="200" /></p:stCondLst></p:cTn><p:tgtEl><p:spTgt spid="{SPID}" /></p:tgtEl><p:attrNameLst><p:attrName>r</p:attrName></p:attrNameLst></p:cBhvr></p:animRot><p:animRot by="240000"><p:cBhvr><p:cTn id="{ID2}" dur="200" fill="hold"><p:stCondLst><p:cond delay="400" /></p:stCondLst></p:cTn><p:tgtEl><p:spTgt spid="{SPID}" /></p:tgtEl><p:attrNameLst><p:attrName>r</p:attrName></p:attrNameLst></p:cBhvr></p:animRot><p:animRot by="-240000"><p:cBhvr><p:cTn id="{ID3}" dur="200" fill="hold"><p:stCondLst><p:cond delay="600" /></p:stCondLst></p:cTn><p:tgtEl><p:spTgt spid="{SPID}" /></p:tgtEl><p:attrNameLst><p:attrName>r</p:attrName></p:attrNameLst></p:cBhvr></p:animRot><p:animRot by="120000"><p:cBhvr><p:cTn id="{ID4}" dur="200" fill="hold"><p:stCondLst><p:cond delay="800" /></p:stCondLst></p:cTn><p:tgtEl><p:spTgt spid="{SPID}" /></p:tgtEl><p:attrNameLst><p:attrName>r</p:attrName></p:attrNameLst></p:cBhvr></p:animRot>